pypemicro/__init__.py
pypemicro/pemicro.py
pypemicro/pemicro_const.py
pypemicro/libs/Linux/unitacmp-64.so
pypemicro/libs/MacOS/libusb.dylib
pypemicro/libs/MacOS/unitacmp-64.dylib
pypemicro/libs/Windows/unitacmp-32.dll
pypemicro/libs/Windows/unitacmp-64.dll
tests/__init__.py
tests/conftest.py
tests/test_basic.py
pypemicro-0.1.11.dist-info/LICENSE
pypemicro-0.1.11.dist-info/METADATA
pypemicro-0.1.11.dist-info/WHEEL
pypemicro-0.1.11.dist-info/top_level.txt
pypemicro-0.1.11.dist-info/RECORD
