Metadata-Version: 2.1
Name: pypemicro
Version: 0.1.11
Summary: Python tool to control PEMicro Debug probes
Home-page: https://github.com/nxpmicro/pypemicro
Download-URL: https://pypi.org/project/pypemicro/
Author: Petr Gargulak
Author-email: petr.gargulak@nxp.com
License: BSD-3-Clause
Keywords: PEMicro,PyPEMicro
Platform: Windows
Platform: Linux
Platform: Mac OSX
Classifier: Programming Language :: Python :: 3.7
Classifier: Programming Language :: Python :: 3.8
Classifier: Programming Language :: Python :: 3.9
Classifier: Programming Language :: Python :: 3.10
Classifier: Programming Language :: Python :: 3.11
Classifier: Operating System :: POSIX :: Linux
Classifier: Operating System :: Microsoft :: Windows
Classifier: Operating System :: MacOS :: MacOS X
Classifier: License :: OSI Approved :: BSD License
Classifier: Topic :: Scientific/Engineering
Classifier: Topic :: Software Development :: Embedded Systems
Classifier: Topic :: System :: Hardware
Classifier: Topic :: Utilities
Requires-Python: >=3.7
License-File: LICENSE
